<annotation>
   <folder>Image</folder>
   <filename>TIM图片20180410143650_18537264.jpg</filename>
   <path>D:\SoftWork\MATLAB\Annotation\Image\TIM图片20180410143650_18537264.jpg</path>
   <source>
      <database>Unknow</database>
   </source>
   <size>
      <width>1443</width>
      <height>1080</height>
      <depth>3</depth>
   </size>
   <segmented>0</segmented>
   <object>
      <name>blasthole</name>
      <pose>Unspecified</pose>
      <truncated>0</truncated>
      <difficult>0</difficult>
      <bndbox>
         <xmin>67</xmin>
         <ymin>287</ymin>
         <xmax>162</xmax>
         <ymax>377</ymax>
      </bndbox>
   </object>
   <object>
      <name>blasthole</name>
      <pose>Unspecified</pose>
      <truncated>0</truncated>
      <difficult>0</difficult>
      <bndbox>
         <xmin>352</xmin>
         <ymin>607</ymin>
         <xmax>444</xmax>
         <ymax>702</ymax>
      </bndbox>
   </object>
   <object>
      <name>blasthole</name>
      <pose>Unspecified</pose>
      <truncated>0</truncated>
      <difficult>0</difficult>
      <bndbox>
         <xmin>822</xmin>
         <ymin>645</ymin>
         <xmax>906</xmax>
         <ymax>738</ymax>
      </bndbox>
   </object>
   <object>
      <name>blasthole</name>
      <pose>Unspecified</pose>
      <truncated>0</truncated>
      <difficult>0</difficult>
      <bndbox>
         <xmin>604</xmin>
         <ymin>643</ymin>
         <xmax>727</xmax>
         <ymax>735</ymax>
      </bndbox>
   </object>
   <object>
      <name>blasthole</name>
      <pose>Unspecified</pose>
      <truncated>0</truncated>
      <difficult>0</difficult>
      <bndbox>
         <xmin>1182</xmin>
         <ymin>317</ymin>
         <xmax>1283</xmax>
         <ymax>431</ymax>
      </bndbox>
   </object>
</annotation>
