<annotation>
   <folder>Image</folder>
   <filename>å·¦æ´žä¸‹å²©å±?ç‚®å­”-2.jpg</filename>
   <path>D:\SoftWork\MATLAB\Annotation\Image\å·¦æ´žä¸‹å²©å±?ç‚®å­”-2.jpg</path>
   <source>
      <database>Unknow</database>
   </source>
   <size>
      <width>4032</width>
      <height>3024</height>
      <depth>3</depth>
   </size>
   <segmented>0</segmented>
   <object>
      <name>blasthole</name>
      <pose>Unspecified</pose>
      <truncated>0</truncated>
      <difficult>0</difficult>
      <bndbox>
         <xmin>311</xmin>
         <ymin>908</ymin>
         <xmax>539</xmax>
         <ymax>1147</ymax>
      </bndbox>
   </object>
   <object>
      <name>blasthole</name>
      <pose>Unspecified</pose>
      <truncated>0</truncated>
      <difficult>0</difficult>
      <bndbox>
         <xmin>213</xmin>
         <ymin>1412</ymin>
         <xmax>373</xmax>
         <ymax>1571</ymax>
      </bndbox>
   </object>
   <object>
      <name>blasthole</name>
      <pose>Unspecified</pose>
      <truncated>0</truncated>
      <difficult>0</difficult>
      <bndbox>
         <xmin>182</xmin>
         <ymin>1805</ymin>
         <xmax>361</xmax>
         <ymax>1977</ymax>
      </bndbox>
   </object>
   <object>
      <name>blasthole</name>
      <pose>Unspecified</pose>
      <truncated>0</truncated>
      <difficult>0</difficult>
      <bndbox>
         <xmin>803</xmin>
         <ymin>1196</ymin>
         <xmax>1006</xmax>
         <ymax>1393</ymax>
      </bndbox>
   </object>
   <object>
      <name>blasthole</name>
      <pose>Unspecified</pose>
      <truncated>0</truncated>
      <difficult>0</difficult>
      <bndbox>
         <xmin>729</xmin>
         <ymin>1737</ymin>
         <xmax>932</xmax>
         <ymax>1922</ymax>
      </bndbox>
   </object>
   <object>
      <name>blasthole</name>
      <pose>Unspecified</pose>
      <truncated>0</truncated>
      <difficult>0</difficult>
      <bndbox>
         <xmin>1319</xmin>
         <ymin>1276</ymin>
         <xmax>1455</xmax>
         <ymax>1418</ymax>
      </bndbox>
   </object>
   <object>
      <name>blasthole</name>
      <pose>Unspecified</pose>
      <truncated>0</truncated>
      <difficult>0</difficult>
      <bndbox>
         <xmin>1276</xmin>
         <ymin>1664</ymin>
         <xmax>1448</xmax>
         <ymax>1830</ymax>
      </bndbox>
   </object>
   <object>
      <name>blasthole</name>
      <pose>Unspecified</pose>
      <truncated>0</truncated>
      <difficult>0</difficult>
      <bndbox>
         <xmin>1793</xmin>
         <ymin>1559</ymin>
         <xmax>2008</xmax>
         <ymax>1768</ymax>
      </bndbox>
   </object>
   <object>
      <name>blasthole</name>
      <pose>Unspecified</pose>
      <truncated>0</truncated>
      <difficult>0</difficult>
      <bndbox>
         <xmin>2278</xmin>
         <ymin>1528</ymin>
         <xmax>2463</xmax>
         <ymax>1719</ymax>
      </bndbox>
   </object>
   <object>
      <name>blasthole</name>
      <pose>Unspecified</pose>
      <truncated>0</truncated>
      <difficult>0</difficult>
      <bndbox>
         <xmin>1811</xmin>
         <ymin>1086</ymin>
         <xmax>1995</xmax>
         <ymax>1301</ymax>
      </bndbox>
   </object>
   <object>
      <name>blasthole</name>
      <pose>Unspecified</pose>
      <truncated>0</truncated>
      <difficult>0</difficult>
      <bndbox>
         <xmin>2364</xmin>
         <ymin>1110</ymin>
         <xmax>2604</xmax>
         <ymax>1313</ymax>
      </bndbox>
   </object>
   <object>
      <name>blasthole</name>
      <pose>Unspecified</pose>
      <truncated>0</truncated>
      <difficult>0</difficult>
      <bndbox>
         <xmin>2899</xmin>
         <ymin>1479</ymin>
         <xmax>3114</xmax>
         <ymax>1694</ymax>
      </bndbox>
   </object>
</annotation>
