<annotation>
   <folder>Image</folder>
   <filename>Ê≠£ÂØπÊéåÂ≠êÈù¢Âè≥‰æß‰∏ãÈÉ®ÁÇÆÂ≠?2_07512384.jpg</filename>
   <path>D:\SoftWork\MATLAB\Annotation\Image\Ê≠£ÂØπÊéåÂ≠êÈù¢Âè≥‰æß‰∏ãÈÉ®ÁÇÆÂ≠?2_07512384.jpg</path>
   <source>
      <database>Unknow</database>
   </source>
   <size>
      <width>4032</width>
      <height>3024</height>
      <depth>3</depth>
   </size>
   <segmented>0</segmented>
   <object>
      <name>blasthole</name>
      <pose>Unspecified</pose>
      <truncated>0</truncated>
      <difficult>0</difficult>
      <bndbox>
         <xmin>858</xmin>
         <ymin>1074</ymin>
         <xmax>1049</xmax>
         <ymax>1283</ymax>
      </bndbox>
   </object>
   <object>
      <name>blasthole</name>
      <pose>Unspecified</pose>
      <truncated>0</truncated>
      <difficult>0</difficult>
      <bndbox>
         <xmin>834</xmin>
         <ymin>1455</ymin>
         <xmax>981</xmax>
         <ymax>1627</ymax>
      </bndbox>
   </object>
   <object>
      <name>blasthole</name>
      <pose>Unspecified</pose>
      <truncated>0</truncated>
      <difficult>0</difficult>
      <bndbox>
         <xmin>797</xmin>
         <ymin>1854</ymin>
         <xmax>963</xmax>
         <ymax>2039</ymax>
      </bndbox>
   </object>
   <object>
      <name>blasthole</name>
      <pose>Unspecified</pose>
      <truncated>0</truncated>
      <difficult>0</difficult>
      <bndbox>
         <xmin>1793</xmin>
         <ymin>1596</ymin>
         <xmax>1940</xmax>
         <ymax>1805</ymax>
      </bndbox>
   </object>
   <object>
      <name>blasthole</name>
      <pose>Unspecified</pose>
      <truncated>0</truncated>
      <difficult>0</difficult>
      <bndbox>
         <xmin>1903</xmin>
         <ymin>1074</ymin>
         <xmax>2082</xmax>
         <ymax>1258</ymax>
      </bndbox>
   </object>
   <object>
      <name>blasthole</name>
      <pose>Unspecified</pose>
      <truncated>0</truncated>
      <difficult>0</difficult>
      <bndbox>
         <xmin>1344</xmin>
         <ymin>1000</ymin>
         <xmax>1504</xmax>
         <ymax>1246</ymax>
      </bndbox>
   </object>
   <object>
      <name>blasthole</name>
      <pose>Unspecified</pose>
      <truncated>0</truncated>
      <difficult>0</difficult>
      <bndbox>
         <xmin>1326</xmin>
         <ymin>1522</ymin>
         <xmax>1461</xmax>
         <ymax>1664</ymax>
      </bndbox>
   </object>
   <object>
      <name>blasthole</name>
      <pose>Unspecified</pose>
      <truncated>0</truncated>
      <difficult>0</difficult>
      <bndbox>
         <xmin>1375</xmin>
         <ymin>1965</ymin>
         <xmax>1528</xmax>
         <ymax>2137</ymax>
      </bndbox>
   </object>
   <object>
      <name>blasthole</name>
      <pose>Unspecified</pose>
      <truncated>0</truncated>
      <difficult>0</difficult>
      <bndbox>
         <xmin>2389</xmin>
         <ymin>1031</ymin>
         <xmax>2543</xmax>
         <ymax>1203</ymax>
      </bndbox>
   </object>
   <object>
      <name>blasthole</name>
      <pose>Unspecified</pose>
      <truncated>0</truncated>
      <difficult>0</difficult>
      <bndbox>
         <xmin>2997</xmin>
         <ymin>1578</ymin>
         <xmax>3157</xmax>
         <ymax>1774</ymax>
      </bndbox>
   </object>
   <object>
      <name>blasthole</name>
      <pose>Unspecified</pose>
      <truncated>0</truncated>
      <difficult>0</difficult>
      <bndbox>
         <xmin>2241</xmin>
         <ymin>1965</ymin>
         <xmax>2450</xmax>
         <ymax>2149</ymax>
      </bndbox>
   </object>
</annotation>
